{
  "title": "古代黑陶烧制工艺科技考古综述",
  "subtitle": "中国陶瓷史及鉴定 · 课程论文汇报",
  "total_pages": 16,
  "framework": "pyramid_principle",
  "cover": {
    "title": "古代黑陶烧制工艺科技考古综述",
    "subtitle": "中国陶瓷史及鉴定 · 课程论文汇报",
    "author": "贾煜琪",
    "affiliation": "南京大学考古文博与中华文明研究院",
    "date": "2026年3月"
  },
  "table_of_contents": {
    "sections": [
      "引言与背景",
      "黑陶分类体系",
      "研究方法体系",
      "误判与挑战",
      "展望与结语"
    ]
  },
  "parts": [
    {
      "title": "Part 1: 引言与背景",
      "key_message": "中西方黑陶虽外观相似，物理化学本质截然不同，需要科技考古方法系统辨析",
      "pages": [
        {
          "index": 3,
          "title": "黑陶：跨越六千年的黑色工艺",
          "subtitle": "定义、分布与历史跨度",
          "type": "content",
          "layout_hint": "two_column_asymmetric",
          "key_points": [
            "黑陶定义：古代先民掌握还原焙烧技术后制作的表面呈黑色陶器",
            "中国分布：大汶口、龙山、跨湖桥、河姆渡、良渚文化",
            "龙山蛋壳黑陶\"黑如漆、薄如纸、亮如镜、硬如瓷\"",
            "地中海分布：古希腊黑绘陶与黑光陶（公元前6世纪）"
          ],
          "data_elements": [
            {
              "type": "table",
              "columns": ["文化/类型", "地域", "关键特征"],
              "rows": [
                ["大汶口文化", "黄河流域", "早期泥质黑陶"],
                ["龙山文化", "山东", "蛋壳黑陶·渗碳"],
                ["良渚文化", "长江下游", "陶衣+磨光"],
                ["古希腊黑光陶", "地中海", "三段式烧成"]
              ]
            }
          ],
          "notes": {
            "talking_points": [
              "黑陶在中国新石器时代中晚期和地中海古典时期都有大量发现",
              "龙山文化蛋壳黑陶是最负盛名的代表",
              "地中海黑光陶采用完全不同的工艺路线"
            ],
            "transition_line": "虽然外观都是黑色，但中西方黑陶的呈色本质截然不同——",
            "timing_seconds": 120
          }
        },
        {
          "index": 4,
          "title": "中西方黑陶的本质差异",
          "subtitle": "相似外观下的不同物理化学机制",
          "type": "comparison",
          "layout_hint": "two_column_symmetric",
          "key_points": [
            "中国黑陶：游离碳沉积（渗碳）为主导呈色",
            "地中海黑陶：涂层中磁铁矿微晶的晶相致色",
            "表面处理差异：封窑渗碳 vs 三段式烧成",
            "物理性能差异：致密度提高 vs 玻璃化耐磨"
          ],
          "data_elements": [
            {
              "type": "table",
              "columns": ["比较维度", "中国黑陶", "地中海黑陶"],
              "rows": [
                ["呈色物质", "游离碳（炭黑）", "磁铁矿微晶"],
                ["核心工艺", "封窑渗碳", "三段式烧成"],
                ["表面处理", "碳沉积填充气孔", "富铁涂层玻化"],
                ["物理性能", "致密度提高", "耐磨性突出"]
              ]
            }
          ],
          "notes": {
            "talking_points": [
              "中国黑陶以碳为呈色物质，地中海以铁氧化物为呈色物质",
              "这一本质差异决定了完全不同的科技判别路径",
              "本文正是从这一分歧出发，建立四大分类体系"
            ],
            "transition_line": "基于呈色物理化学本质的差异，我们可以将古代黑陶归纳为四大工艺类型——",
            "timing_seconds": 90
          }
        }
      ]
    },
    {
      "title": "Part 2: 黑陶分类体系",
      "key_message": "古代黑陶按呈色物理化学本质分为四大工艺类型：铁致黑、碳致黑、晶相致黑、结构致黑",
      "pages": [
        {
          "index": 5,
          "title": "四大工艺类型总览",
          "subtitle": "以呈色物质的物理化学本质为分类主干",
          "type": "data",
          "layout_hint": "dashboard",
          "key_points": [
            "还原焙烧（铁致黑）：Fe₃O₄/FeO",
            "渗碳（碳致黑）：游离碳（炭黑）",
            "三段式烧成（晶相致黑）：磁铁矿/赫赛石微晶涂层",
            "抛光（结构致黑）：矿物定向排列"
          ],
          "data_elements": [
            {
              "type": "table",
              "columns": ["工艺类型", "呈色物质", "典型代表", "核心判别手段"],
              "rows": [
                ["还原焙烧（铁致黑）", "Fe₃O₄/FeO", "仰韶深灰陶", "XRD+复烧变红"],
                ["渗碳（碳致黑）", "游离碳", "龙山蛋壳黑陶", "Raman D/G峰"],
                ["三段式烧成（晶相致黑）", "磁铁矿微晶涂层", "雅典黑光陶", "SEM-BSE+SR-μXRD"],
                ["抛光（结构致黑）", "矿物定向排列", "百济研磨黑陶", "PLM+EBSD"]
              ]
            }
          ],
          "notes": {
            "talking_points": [
              "这是论文的核心创新点——以呈色物理化学本质为分类主干",
              "四大类型覆盖了中国和地中海的主要黑陶类型",
              "实际考古遗物中两种甚至三种工艺叠加并不罕见"
            ],
            "transition_line": "下面我们逐一来看每种工艺的呈色机理——",
            "timing_seconds": 120
          }
        },
        {
          "index": 6,
          "title": "还原焙烧（铁致黑）",
          "subtitle": "Fe₂O₃ → Fe₃O₄ → FeO 的还原链",
          "type": "content",
          "layout_hint": "hero_grid",
          "key_points": [
            "最基础的黑陶呈色途径",
            "缺氧窑炉气氛中赤铁矿被还原为磁铁矿或方铁矿",
            "Fe₂O₃含量>5%且氧分压足够低时呈接近黑色的深灰",
            "冷却需保持隔氧，否则\"返红\""
          ],
          "data_elements": [
            {
              "type": "metric",
              "label": "Fe₂O₃含量阈值",
              "value": ">5%",
              "unit": "",
              "delta": ""
            },
            {
              "type": "metric",
              "label": "磁铁矿形成温度",
              "value": "700-900",
              "unit": "°C",
              "delta": ""
            }
          ],
          "notes": {
            "talking_points": [
              "还原焙烧是最基础也最古老的黑陶呈色途径",
              "核心判别：XRD磁铁矿峰 + 复烧变红 + 热重无碳燃烧失重",
              "Nodari等在意大利伊特鲁里亚夹心陶中发现Fe²⁺/Fe³⁺梯度"
            ],
            "transition_line": "接下来看中国新石器时代最主要的呈色工艺——渗碳——",
            "timing_seconds": 90
          }
        },
        {
          "index": 7,
          "title": "渗碳（碳致黑）",
          "subtitle": "中国新石器时代黑陶最主要的呈色工艺",
          "type": "content",
          "layout_hint": "mixed_grid",
          "key_points": [
            "有机燃料不完全燃烧产生碳黑颗粒",
            "两种沉积途径：物理充填 + 化学歧化反应（2CO→CO₂+C）",
            "刘鹏实验：630°C以下渗碳效果最佳",
            "李文杰复原四种渗碳模式：全身皆黑/外红内黑/上红下黑/竖条黑道"
          ],
          "data_elements": [
            {
              "type": "metric",
              "label": "渗碳温度窗口上限",
              "value": "630",
              "unit": "°C",
              "delta": ""
            },
            {
              "type": "metric",
              "label": "Raman D峰",
              "value": "~1350",
              "unit": "cm⁻¹",
              "delta": ""
            },
            {
              "type": "metric",
              "label": "Raman G峰",
              "value": "~1580",
              "unit": "cm⁻¹",
              "delta": ""
            }
          ],
          "notes": {
            "talking_points": [
              "渗碳是中国黑陶研究中最核心的工艺类型",
              "刘鹏的实验表明630°C以下粘土矿物仍保留层间水，吸附能力最强",
              "拉曼光谱D/G峰和EDS碳梯度线扫描是核心判别手段"
            ],
            "transition_line": "与中国渗碳黑陶截然不同，地中海黑光陶采用三段式烧成——",
            "timing_seconds": 120
          }
        },
        {
          "index": 8,
          "title": "三段式烧成（晶相致黑）",
          "subtitle": "氧化—还原—再氧化：地中海黑光陶的选择性致色",
          "type": "process",
          "layout_hint": "timeline",
          "key_points": [
            "第I阶段：氧化升温至~800°C，涂层与胎体均为Fe₂O₃赤铁矿",
            "第II阶段：还原850-950°C，Fe₂O₃→Fe₃O₄，涂层开始烧结玻化",
            "第III阶段：再氧化降至~800°C，涂层致密保黑，胎体疏松返红",
            "选择性致色关键：涂层粒径<2μm + K₂O/CaO助熔剂 → 低温即烧结封孔"
          ],
          "data_elements": [
            {
              "type": "chart",
              "chart_type": "timeline",
              "data_points": [
                {"label": "I 氧化", "value": "~800°C", "desc": "Fe₂O₃ 赤铁矿"},
                {"label": "II 还原", "value": "850-950°C", "desc": "Fe₂O₃→Fe₃O₄ 玻化"},
                {"label": "III 再氧化", "value": "~800°C", "desc": "涂层保黑·胎体返红"}
              ]
            }
          ],
          "notes": {
            "talking_points": [
              "三段式烧成是地中海黑光陶的核心工艺",
              "关键在于涂层与胎体对氧气渗透的差异响应",
              "Cianchetta等确认涂层黑色相为磁铁矿和赫赛石微晶"
            ],
            "transition_line": "最后一种工艺类型更为特别——不依赖化学变化，而是物理结构——",
            "timing_seconds": 120
          }
        },
        {
          "index": 9,
          "title": "抛光（结构致黑）",
          "subtitle": "矿物定向排列消除漫反射",
          "type": "content",
          "layout_hint": "two_column_asymmetric",
          "key_points": [
            "不依赖碳沉积或铁物相改变",
            "精细磨光使层状硅酸盐矿物定向排列，消除可见光漫反射",
            "Kim等：百济黑陶未检测到碳沉积或涂层，呈色完全归因于矿物排列",
            "PLM偏光消光 + EBSD织构分析 + AFM表面粗糙度测量"
          ],
          "data_elements": [],
          "notes": {
            "talking_points": [
              "结构致黑是最容易被忽视的一种机制",
              "百济汉城期黑陶是最典型的案例",
              "Blackmore指出研磨抛光具有社会等级标识功能"
            ],
            "transition_line": "了解了四种工艺类型后，我们来看如何用科技手段加以判别——",
            "timing_seconds": 90
          }
        }
      ]
    },
    {
      "title": "Part 3: 研究方法体系",
      "key_message": "科技判别已形成从无损筛查到微区定量的层级化分析方法体系",
      "pages": [
        {
          "index": 10,
          "title": "层级化分析方法体系",
          "subtitle": "无损筛查 → 微损定性 → 微区定量",
          "type": "data",
          "layout_hint": "horizontal_split",
          "key_points": [
            "无损筛查：体视显微镜、便携XRF、色度计",
            "微损定性：拉曼光谱、FTIR、偏光显微镜",
            "微区定量：SEM-EDS、穆斯堡尔谱、SR-μXRD、EBSD"
          ],
          "data_elements": [
            {
              "type": "table",
              "columns": ["分析层级", "代表方法", "获取信息"],
              "rows": [
                ["无损筛查", "体视显微镜·便携XRF·色度计", "表面形貌·主量元素·颜色参数"],
                ["微损定性", "拉曼光谱·FTIR·偏光显微镜", "碳/铁物相·矿物种类"],
                ["微区定量", "SEM-EDS·穆斯堡尔谱·SR-μXRD", "元素分布·铁价态·微晶物相"]
              ]
            }
          ],
          "notes": {
            "talking_points": [
              "方法体系从无损到微区定量层层递进",
              "无损筛查适用于所有工艺类型的初步判断",
              "微区定量为精确判定提供核心数据"
            ],
            "transition_line": "下面对比一下各方法在黑陶研究中的适用性——",
            "timing_seconds": 90
          }
        },
        {
          "index": 11,
          "title": "主要分析方法比较",
          "subtitle": "各方法的检测对象、优势与局限",
          "type": "data",
          "layout_hint": "single_focus",
          "key_points": [
            "拉曼光谱：碳相与铁氧化物检测，无损但荧光干扰严重",
            "XRD：物相鉴定准确但需粉末样品",
            "穆斯堡尔谱：铁价态定量精确但需~100mg样品",
            "SEM-EDS：微区信息丰富但需真空与制样"
          ],
          "data_elements": [
            {
              "type": "table",
              "columns": ["方法", "检测对象", "优势", "局限"],
              "rows": [
                ["拉曼光谱", "碳相·铁氧化物", "无损·高空间分辨率", "荧光干扰"],
                ["XRD", "矿物相", "物相鉴定准确", "需粉末样品"],
                ["穆斯堡尔谱", "Fe价态", "铁价态定量精确", "需~100mg样品"],
                ["SEM-EDS", "形貌·元素", "微区信息丰富", "需真空·制样有损"],
                ["FTIR", "有机质·矿物", "样品需求少", "空间分辨率低"],
                ["SR-μXRD", "微晶物相", "空间分辨率极高", "依赖同步辐射光源"]
              ]
            }
          ],
          "notes": {
            "talking_points": [
              "没有一种方法能够解决所有问题，需要多方法联用",
              "拉曼和SEM-EDS是使用最广泛的组合",
              "穆斯堡尔谱对还原焙烧黑陶的判别尤为关键"
            ],
            "transition_line": "然而，实际分析中存在不少误判风险——",
            "timing_seconds": 120
          }
        }
      ]
    },
    {
      "title": "Part 4: 误判与挑战",
      "key_message": "埋藏环境干扰和工艺多解性是当前面临的核心挑战，需多元互证",
      "pages": [
        {
          "index": 12,
          "title": "埋藏环境干扰",
          "subtitle": "锰沉积、有机质吸附与钙质结壳",
          "type": "content",
          "layout_hint": "three_column",
          "key_points": [
            "锰的二次沉积：锰氧化物薄膜与渗碳层外观极似，EDS面扫描中Mn异常富集",
            "有机质次生吸附：腐殖酸渗入气孔，荧光效应掩盖碳D/G特征峰",
            "钙质结壳：覆盖器表干扰化学成分测定，需显微鉴定并小心去除"
          ],
          "data_elements": [],
          "notes": {
            "talking_points": [
              "De Vito等在西西里莫提亚遗址发现部分黑色区域实为埋藏期锰氧化物",
              "Scarpelli等在庞贝遇到严重荧光干扰，最终靠FTIR+SEM-EDS解决",
              "Laciak等指出钙质结壳在分析前需小心去除"
            ],
            "transition_line": "除了埋藏干扰，工艺本身的多解性也是重大挑战——",
            "timing_seconds": 90
          }
        },
        {
          "index": 13,
          "title": "工艺多解性难题",
          "subtitle": "同一物相 ≠ 同一工艺",
          "type": "content",
          "layout_hint": "hero_grid",
          "key_points": [
            "磁铁矿的双重来源：既可是还原焙烧产物，也可是三段式涂层中的微晶",
            "良渚案例：胎体有机质草木灰形成低磷泥浆层而非专门陶衣",
            "应对策略：多元互证原则——至少两种独立方法交叉验证",
            "有损vs无损矛盾：蛋壳黑陶等珍贵器物难以接受有损取样"
          ],
          "data_elements": [],
          "notes": {
            "talking_points": [
              "仅凭XRD检测到磁铁矿无法判断是整体还原还是涂层局部还原",
              "鲁晓珂等发现良渚黑陶工艺比预想更复杂",
              "Amicone等强调实验复原与分析数据对照的重要性"
            ],
            "transition_line": "这些挑战推动研究者将目光转向新兴技术——",
            "timing_seconds": 90
          }
        }
      ]
    },
    {
      "title": "Part 5: 展望与结语",
      "key_message": "新兴原位无损技术与跨文化比较将推动黑陶工艺研究迈入新阶段",
      "pages": [
        {
          "index": 14,
          "title": "新兴技术与未来展望",
          "subtitle": "原位无损分析的新途径",
          "type": "data",
          "layout_hint": "dashboard",
          "key_points": [
            "SR-μXRD：10μm空间尺度无损物相分析",
            "XANES：不取样测定铁价态与配位环境",
            "Micro-CT：三维重建胎体气孔形态与渗碳深度",
            "HR-TEM：揭示涂层纳米级微晶的晶体学特征"
          ],
          "data_elements": [
            {
              "type": "table",
              "columns": ["技术", "核心能力", "应用前景"],
              "rows": [
                ["SR-μXRD", "≤10μm物相分析", "无损微区物相"],
                ["XANES", "原位铁价态测定", "还原/三段式判别"],
                ["Micro-CT", "3D气孔重建", "渗碳深度评估"],
                ["HR-TEM", "纳米级晶体学", "涂层微晶精细表征"]
              ]
            }
          ],
          "notes": {
            "talking_points": [
              "这些新技术的共同方向是原位、无损、高空间分辨率",
              "Reedy等用Micro-CT表征了42个孔隙参数，26个与烧成温度显著相关",
              "Choi等证明穆斯堡尔谱+XRD+磁性测量能提供常规方法难获取的信息"
            ],
            "transition_line": "最后，让我们回到宏观视角总结全文——",
            "timing_seconds": 90
          }
        },
        {
          "index": 15,
          "title": "中西方工艺的平行之路",
          "subtitle": "两条技术路线，同一个本质",
          "type": "comparison",
          "layout_hint": "two_column_symmetric",
          "key_points": [
            "中国先民：封窑渗碳 → 控制碳沉积实现器表变黑",
            "地中海工匠：三段式烧成 → 胶体化学原理制备富铁涂层",
            "共同本质：对窑炉气氛和表面微观结构的精密控制",
            "跨文化比较有助于揭示人类材料技术发展的共性与差异"
          ],
          "data_elements": [
            {
              "type": "table",
              "columns": ["维度", "中国先民", "地中海工匠"],
              "rows": [
                ["核心工艺", "封窑渗碳", "三段式烧成"],
                ["呈色机制", "碳沉积变黑", "胶体化学选择性致色"],
                ["技术本质", "窑炉气氛精密控制", "气氛+微观结构双重控制"]
              ]
            }
          ],
          "notes": {
            "talking_points": [
              "中西方黑陶工艺是人类制陶技术演进的两条平行路线",
              "虽然具体做法不同，本质上都是对窑炉气氛的精密控制",
              "这种跨文化比较正是科技考古的独特价值"
            ],
            "transition_line": "",
            "timing_seconds": 90
          }
        }
      ]
    }
  ],
  "end_page": {
    "type": "thank_you",
    "title": "感谢聆听",
    "content": "贾煜琪 · 南京大学考古文博与中华文明研究院\n指导教师：王晓琪\n敬请批评指正"
  }
}
